webview/__init__.py
webview/event.py
webview/guilib.py
webview/http.py
webview/localization.py
webview/menu.py
webview/screen.py
webview/util.py
webview/window.py
webview/js/__init__.py
webview/js/alert.py
webview/js/api.py
webview/js/css.py
webview/js/dom.py
webview/js/drag.py
webview/js/event.py
webview/js/npo.py
webview/lib/Microsoft.Web.WebView2.Core.dll
webview/lib/Microsoft.Web.WebView2.LICENSE.md
webview/lib/Microsoft.Web.WebView2.WinForms.dll
webview/lib/WebBrowserInterop.x64.dll
webview/lib/WebBrowserInterop.x86.dll
webview/lib/arm64/WebView2Loader.dll
webview/lib/x64/WebView2Loader.dll
webview/lib/x86/WebView2Loader.dll
webview/platforms/__init__.py
webview/platforms/cef.py
webview/platforms/cocoa.py
webview/platforms/edgechromium.py
webview/platforms/gtk.py
webview/platforms/mshtml.py
webview/platforms/qt.py
webview/platforms/winforms.py
pequenawebview-4.1.3.dist-info/LICENSE.md
pequenawebview-4.1.3.dist-info/METADATA
pequenawebview-4.1.3.dist-info/WHEEL
pequenawebview-4.1.3.dist-info/top_level.txt
pequenawebview-4.1.3.dist-info/RECORD
